<TableSpec 
	xmlns="bb_appfx_table"
	xmlns:common="bb_appfx_commontypes" 
	ID="1f38b824-86ff-4a36-88a7-978dd9ec5a92"
	Name="TESTINGONLY"
	Description="For Testing Only--Do not use!"
	Author="memphis"
	Tablename="USR_TESTINGONLY"		   
	>

	<!-- define fields on the table -->
	<Fields>
		<MemoField Description="Testing Memo Field" Name="TESTMEMO"/>
		<TextField Description="Testing Text" Length="50" Name="TESTINGTEXT"/>
	</Fields>

	<!-- define any additional check constraints on the table --><!--
	<CheckConstraints>

	</CheckConstraints>

	--><!-- define any indexes on the table --><!--
	<Indexes>

	</Indexes>
		
	--><!-- define any triggers on the table --><!--
	<Triggers>

	</Triggers>-->

</TableSpec>
